odt_to_pdf/__init__.py
odt_to_pdf/conversion.py
odt_to_pdf/queue_name.py
odt_to_pdf-1.0.3.dist-info/LICENSE
odt_to_pdf-1.0.3.dist-info/WHEEL
odt_to_pdf-1.0.3.dist-info/METADATA
odt_to_pdf-1.0.3.dist-info/RECORD
