Metadata-Version: 2.1
Name: odt_to_pdf
Version: 1.0.3
Summary: Celery task to generate a PDF from a LibreOffice document (mostly ODT).
Author-email: Matiboy <matt.cc.kho@gmail.com>
Requires-Python: >=3.5
Classifier: License :: OSI Approved :: MIT License
Requires-Dist: celery >=4
